coffeescript/__init__.py
coffeescript/coffee-script.js
CoffeeScript-1.0.9.dist-info/METADATA
CoffeeScript-1.0.9.dist-info/WHEEL
CoffeeScript-1.0.9.dist-info/top_level.txt
CoffeeScript-1.0.9.dist-info/RECORD
CoffeeScript-1.0.9.dist-info/metadata.json
CoffeeScript-1.0.9.dist-info/DESCRIPTION.rst
