Metadata-Version: 2.0
Name: CoffeeScript
Version: 1.0.9
Summary: A bridge to the JS CoffeeScript compiler
Home-page: https://github.com/doloopwhile/Python-CoffeeScript
Author: OMOTO Kenji
Author-email: doloopwhile@gmail.com
License: MIT License
Download-URL: https://pypi.python.org/pypi/CoffeeScript
Platform: UNKNOWN
Classifier: Development Status :: 5 - Production/Stable
Classifier: Intended Audience :: Developers
Classifier: Natural Language :: English
Classifier: License :: OSI Approved :: MIT License
Classifier: Programming Language :: Python
Classifier: Programming Language :: Python :: 2
Classifier: Programming Language :: Python :: 2.6
Classifier: Programming Language :: Python :: 2.7
Classifier: Programming Language :: Python :: 3
Classifier: Programming Language :: Python :: 3.1
Classifier: Programming Language :: Python :: 3.2
Classifier: Programming Language :: JavaScript
Requires-Dist: PyExecJS
